imagesize/__init__.py
imagesize/imagesize.py
approck_imagesize-1.4.1.dist-info/METADATA
approck_imagesize-1.4.1.dist-info/WHEEL
approck_imagesize-1.4.1.dist-info/licenses/LICENSE.rst
approck_imagesize-1.4.1.dist-info/RECORD
