Metadata-Version: 2.4
Name: approck-imagesize
Version: 1.4.1
Summary: Getting image size from png/jpeg/jpeg2000/gif file
License-File: LICENSE.rst
Author: Yoshiki Shibukawa
Author-email: yoshiki@shibu.jp
Requires-Python: >=3.10
Classifier: Programming Language :: Python :: 3
Classifier: Programming Language :: Python :: 3.10
Classifier: Programming Language :: Python :: 3.11
Classifier: Programming Language :: Python :: 3.12
Classifier: Programming Language :: Python :: 3.13
Classifier: Programming Language :: Python :: 3.14
